LICENSE
MANIFEST.in
README.md
README.rst
setup.py
django_search_statistic.egg-info/PKG-INFO
django_search_statistic.egg-info/SOURCES.txt
django_search_statistic.egg-info/dependency_links.txt
django_search_statistic.egg-info/requires.txt
django_search_statistic.egg-info/top_level.txt
search_statistic/__init__.py
search_statistic/admin.py
search_statistic/forms.py
search_statistic/middleware.py
search_statistic/models.py
search_statistic/tests.py
search_statistic/views.py
search_statistic/locale/ru/LC_MESSAGES/django.mo
search_statistic/locale/ru/LC_MESSAGES/django.po
search_statistic/migrations/0001_initial.py
search_statistic/migrations/__init__.py
search_statistic/utils/__init__.py
search_statistic/utils/search_engine.py
search_statistic/utils/visits.py