Metadata-Version: 1.1
Name: django-search-statistic
Version: 0.0.2
Summary: Provide search statistic for Django framework.
Home-page: http://django-search-statistic.beslave.net/
Author: Vladislav Lozhechnik
Author-email: lozhechnik.vladislav@gmail.com
License: GNU v2 License
Platform: UNKNOWN
Classifier: Environment :: Web Environment
Classifier: Framework :: Django
Classifier: Intended Audience :: Developers
Classifier: License :: OSI Approved :: BSD License
Classifier: Operating System :: OS Independent
Classifier: Programming Language :: Python
Classifier: Programming Language :: Python :: 2.6
Classifier: Programming Language :: Python :: 2.7
Classifier: Topic :: Internet :: WWW/HTTP
Classifier: Topic :: Internet :: WWW/HTTP :: Dynamic Content
